wikidataintegrator/__init__.py
wikidataintegrator/sdc_core.py
wikidataintegrator/wdi_backoff.py
wikidataintegrator/wdi_config.py
wikidataintegrator/wdi_core.py
wikidataintegrator/wdi_fastrun.py
wikidataintegrator/wdi_login.py
wikidataintegrator/wdi_rdf.py
wikidataintegrator/ref_handlers/__init__.py
wikidataintegrator/ref_handlers/strict_overwrite.py
wikidataintegrator/ref_handlers/test_update_retrieved_if_new.py
wikidataintegrator/ref_handlers/update_release.py
wikidataintegrator/ref_handlers/update_retrieved_if_new.py
wikidataintegrator/ref_handlers/update_retrieved_if_new_multiple_refs.py
wikidataintegrator/tests/__init__.py
wikidataintegrator/tests/test_backoff.py
wikidataintegrator/tests/test_fastrun.py
wikidataintegrator/tests/test_handle_refs.py
wikidataintegrator/tests/test_item_creation.py
wikidataintegrator/tests/test_item_generator.py
wikidataintegrator/tests/test_wd_search.py
wikidataintegrator/tests/test_wdi_helpers.py
wikidataintegrator/tests/test_wdi_login.py
wikidataintegrator/tests/tests.py
wikidataintegrator/wdi_helpers/__init__.py
wikidataintegrator/wdi_helpers/mapping_relation_helper.py
wikidataintegrator/wdi_helpers/publication.py
wikidataintegrator/wdi_helpers/release.py
wikidataintegrator/wdi_helpers/wikibase_helper.py
wikidataintegrator-0.9.30.dist-info/LICENSE.txt
wikidataintegrator-0.9.30.dist-info/METADATA
wikidataintegrator-0.9.30.dist-info/WHEEL
wikidataintegrator-0.9.30.dist-info/entry_points.txt
wikidataintegrator-0.9.30.dist-info/top_level.txt
wikidataintegrator-0.9.30.dist-info/RECORD
