Metadata-Version: 2.1
Name: wikidataintegrator
Version: 0.9.30
Summary: Python package for reading and writing to/from Wikidata
Home-page: https://github.com/sulab/WikidataIntegrator
Author: Andra Waagmeester, Greg Stupp, Sebastian Burgstaller-Muehlbacher 
Author-email: andra@micel.io
License: MIT
Keywords: Wikidata genewiki biology chemistry medicine ShEx citations
Classifier: Programming Language :: Python :: 3.7
Classifier: Programming Language :: Python :: 3.8
Classifier: Programming Language :: Python :: 3.9
Classifier: Programming Language :: Python :: 3.9
Classifier: Development Status :: 4 - Beta
Classifier: Operating System :: POSIX
Classifier: Operating System :: MacOS :: MacOS X
Classifier: Operating System :: Microsoft :: Windows
Classifier: Intended Audience :: Science/Research
Classifier: Intended Audience :: Information Technology
Classifier: Intended Audience :: Healthcare Industry
Classifier: Intended Audience :: Developers
Classifier: Topic :: Utilities
Classifier: Topic :: Scientific/Engineering :: Bio-Informatics
License-File: LICENSE.txt
Requires-Dist: requests
Requires-Dist: python-dateutil
Requires-Dist: simplejson
Requires-Dist: pandas
Requires-Dist: tqdm
Requires-Dist: mwoauth
Requires-Dist: oauthlib
Requires-Dist: jsonasobj
Requires-Dist: pyshex
Requires-Dist: backoff
Requires-Dist: shexer
